cosupply/__init__.py
cosupply-0.0.0.dist-info/LICENSE
cosupply-0.0.0.dist-info/METADATA
cosupply-0.0.0.dist-info/WHEEL
cosupply-0.0.0.dist-info/top_level.txt
cosupply-0.0.0.dist-info/RECORD
